[{"Latitude": 34.99911, "Longitude": 33.08105, "Pool": "No", "Vegetation": "Medium", "Subsidence": "Low", "Landslides": "Moderate", "Wildfires": "No", "Burnt": "No", "Aspect": 263, "Slope": 5, "SlopeCoef": 0.05, "AspectDir": "West", "SoilDepth": 0.023, "SoilTexture": "Loamy sand", "GeoZone": "Suitable", "AvgRain": 0.2, "Rain": "Low", "Heightlvl": 0.0582, "Elevationlvl": "Level Two", "Land use": "Dense forest", "Height": 582, "Unit": "meters", "Score": 0, "Risk": "Healthy", "WindSpd": 7.2, "WindDrn": "NW", "WindClass": "Fresh to Strong", "TreeType": "Carrop"}, {"Latitude": 34.9788, "Longitude": 33.07262, "Pool": "Yes", "Vegetation": "No", "Subsidence": "High", "Landslides": "Moderate", "Wildfires": "No", "Burnt": "No", "Aspect": 339, "Slope": 68, "SlopeCoef": 0.68, "AspectDir": "East", "SoilDepth": 0.082, "SoilTexture": "Clay", "GeoZone": "Marginally Suitable", "AvgRain": 0.227, "Rain": "Low", "Heightlvl": 0.0701, "Elevationlvl": "Level Two", "Land use": "Mining field", "Height": 701, "Unit": "meters", "Score": 0, "Risk": "Healthy", "WindSpd": 1.9, "WindDrn": "NNE", "WindClass": "Light Air", "TreeType": "Olive"}, {"Latitude": 34.89559, "Longitude": 33.2517, "Pool": "Yes", "Vegetation": "No", "Subsidence": "High", "Landslides": "No", "Wildfires": "Medium", "Burnt": "No", "Aspect": 192, "Slope": 56, "SlopeCoef": 0.56, "AspectDir": "North", "SoilDepth": 0.049, "SoilTexture": "Loamy sand", "GeoZone": "Moderately Suitable", "AvgRain": 0.426, "Rain": "Normal", "Heightlvl": 0.0157, "Elevationlvl": "Level One", "Land use": "Sparse residential", "Height": 157, "Unit": "meters", "Score": 0, "Risk": "Healthy", "WindSpd": 2.4, "WindDrn": "SE", "WindClass": "Light Air", "TreeType": "Fig"}, {"Latitude": 34.88957, "Longitude": 33.24662, "Pool": "Yes", "Vegetation": "High", "Subsidence": "Low", "Landslides": "Moderate", "Wildfires": "Low", "Burnt": "No", "Aspect": 59, "Slope": 75, "SlopeCoef": 0.75, "AspectDir": "East", "SoilDepth": 0.103, "SoilTexture": "Clay", "GeoZone": "Moderately Suitable", "AvgRain": 0.042, "Rain": "Low", "Heightlvl": 0.0069, "Elevationlvl": "Level One", "Land use": "Urban green", "Height": 69, "Unit": "meters", "Score": 0, "Risk": "Healthy", "WindSpd": 15.4, "WindDrn": "NE", "WindClass": "Very Strong Wind", "TreeType": "Olive"}, {"Latitude": 34.86441, "Longitude": 33.19763, "Pool": "No", "Vegetation": "Medium", "Subsidence": "Low", "Landslides": "No", "Wildfires": "Very High", "Burnt": "Slightly", "Aspect": 140, "Slope": 63, "SlopeCoef": 0.63, "AspectDir": "East", "SoilDepth": 0.006, "SoilTexture": "Loamy sand", "GeoZone": "Moderately Suitable", "AvgRain": 0.681, "Rain": "High", "Heightlvl": 0.0281, "Elevationlvl": "Level One", "Land use": "Industry", "Height": 281, "Unit": "meters", "Score": 0.5, "Risk": "Water Stressed", "WindSpd": 14.7, "WindDrn": "NW", "WindClass": "Very Strong Wind", "TreeType": "Olive"}]